minitouch_py-1.1.2.dist-info/licenses/LICENSE
minitouchpy/__init__.py
minitouchpy/actions.py
minitouchpy/const.py
minitouchpy/logger.py
minitouchpy/mnt.py
minitouchpy/utils.py
minitouch_py-1.1.2.dist-info/METADATA
minitouch_py-1.1.2.dist-info/WHEEL
minitouch_py-1.1.2.dist-info/top_level.txt
minitouch_py-1.1.2.dist-info/RECORD
